funkwhale_api/__init__.py
funkwhale_api/activity/__init__.py
funkwhale_api/activity/apps.py
funkwhale_api/activity/record.py
funkwhale_api/activity/serializers.py
funkwhale_api/activity/utils.py
funkwhale_api/activity/views.py
funkwhale_api/audio/__init__.py
funkwhale_api/audio/admin.py
funkwhale_api/audio/categories.py
funkwhale_api/audio/dynamic_preferences_registry.py
funkwhale_api/audio/factories.py
funkwhale_api/audio/filters.py
funkwhale_api/audio/migrations/0001_initial.py
funkwhale_api/audio/migrations/0002_channel_metadata.py
funkwhale_api/audio/migrations/0003_channel_rss_url.py
funkwhale_api/audio/migrations/0004_alter_channel_metadata.py
funkwhale_api/audio/migrations/__init__.py
funkwhale_api/audio/models.py
funkwhale_api/audio/renderers.py
funkwhale_api/audio/serializers.py
funkwhale_api/audio/spa_views.py
funkwhale_api/audio/tasks.py
funkwhale_api/audio/views.py
funkwhale_api/cli/__init__.py
funkwhale_api/cli/base.py
funkwhale_api/cli/library.py
funkwhale_api/cli/main.py
funkwhale_api/cli/media.py
funkwhale_api/cli/plugins.py
funkwhale_api/cli/users.py
funkwhale_api/cli/utils.py
funkwhale_api/common/__init__.py
funkwhale_api/common/admin.py
funkwhale_api/common/apps.py
funkwhale_api/common/authentication.py
funkwhale_api/common/cache.py
funkwhale_api/common/channels.py
funkwhale_api/common/consumers.py
funkwhale_api/common/decorators.py
funkwhale_api/common/dynamic_preferences_registry.py
funkwhale_api/common/factories.py
funkwhale_api/common/fields.py
funkwhale_api/common/filters.py
funkwhale_api/common/locales.py
funkwhale_api/common/management/__init__.py
funkwhale_api/common/management/commands/__init__.py
funkwhale_api/common/management/commands/gitpod.py
funkwhale_api/common/management/commands/load_test_data.py
funkwhale_api/common/management/commands/makemigrations.py
funkwhale_api/common/management/commands/migrate.py
funkwhale_api/common/management/commands/script.py
funkwhale_api/common/middleware.py
funkwhale_api-1.2.8.dist-info/WHEEL
funkwhale_api-1.2.8.dist-info/METADATA
funkwhale_api-1.2.8.dist-info/RECORD
