Metadata-Version: 2.1
Name: funkwhale-api
Version: 1.2.8
Summary: 
License: GNU AGPLv3
Author: Funkwhale Collective
Requires-Python: >=3.7,<4.0
Classifier: License :: Other/Proprietary License
Classifier: Programming Language :: Python :: 3
Classifier: Programming Language :: Python :: 3.7
Classifier: Programming Language :: Python :: 3.8
Classifier: Programming Language :: Python :: 3.9
Classifier: Programming Language :: Python :: 3.10
Classifier: Programming Language :: Python :: 3.11
Requires-Dist: Django (==3.2.16)
Requires-Dist: Markdown (==3.4.1)
Requires-Dist: Pillow (==9.3.0)
Requires-Dist: PyLD (==2.0.3)
Requires-Dist: aiohttp (==3.8.3)
Requires-Dist: arrow (==1.2.3)
Requires-Dist: asgiref (==3.5.2)
Requires-Dist: bleach (==5.0.1)
Requires-Dist: boto3 (==1.25.4)
Requires-Dist: celery (==5.2.7)
Requires-Dist: channels (==3.0.5)
Requires-Dist: channels-redis (==3.4.1)
Requires-Dist: click (==8.1.3)
Requires-Dist: cryptography (==37.0.4)
Requires-Dist: dj-rest-auth[with-social] (==2.2.5)
Requires-Dist: django-allauth (==0.42.0)
Requires-Dist: django-auth-ldap (==4.1.0)
Requires-Dist: django-cache-memoize (==0.1.10)
Requires-Dist: django-cacheops (==6.1)
Requires-Dist: django-cleanup (==6.0.0)
Requires-Dist: django-cors-headers (==3.13.0)
Requires-Dist: django-dynamic-preferences (==1.14.0)
Requires-Dist: django-environ (==0.9.0)
Requires-Dist: django-filter (==22.1)
Requires-Dist: django-oauth-toolkit (==1.7.1)
Requires-Dist: django-redis (==5.2.0)
Requires-Dist: django-storages (==1.13.1)
Requires-Dist: django-versatileimagefield (==2.2)
Requires-Dist: djangorestframework (==3.13.1)
Requires-Dist: drf-spectacular (==0.23.1)
Requires-Dist: feedparser (==6.0.10)
Requires-Dist: gunicorn (==20.1.0)
Requires-Dist: importlib_metadata (==4.13.0); python_full_version <= "3.7.0"
Requires-Dist: ipython (==7.34.0)
Requires-Dist: kombu (==5.2.4)
Requires-Dist: musicbrainzngs (==0.7.1)
Requires-Dist: mutagen (==1.45.1)
Requires-Dist: persisting-theory (==1.0)
Requires-Dist: pluralizer (==1.2.0)
Requires-Dist: psycopg2 (==2.9.5)
Requires-Dist: pyOpenSSL (==21.0.0)
Requires-Dist: pydub (==0.25.1)
Requires-Dist: python-ldap (==3.4.3)
Requires-Dist: python-magic (==0.4.27)
Requires-Dist: pytz (==2022.2.1)
Requires-Dist: redis (==4.3.4)
Requires-Dist: requests (==2.28.1)
Requires-Dist: requests-http-message-signatures (==0.3.1)
Requires-Dist: sentry-sdk (==1.9.8)
Requires-Dist: service-identity (==21.1.0)
Requires-Dist: unicode-slugify (==0.1.5)
Requires-Dist: uvicorn[standard] (==0.18.3)
Requires-Dist: watchdog (==2.1.9)
